LICENSE
MANIFEST.in
README.md
requirements.txt
setup.py
src/pii_process/__init__.py
src/pii_process.egg-info/PKG-INFO
src/pii_process.egg-info/SOURCES.txt
src/pii_process.egg-info/dependency_links.txt
src/pii_process.egg-info/entry_points.txt
src/pii_process.egg-info/requires.txt
src/pii_process.egg-info/top_level.txt
src/pii_process/api/__init__.py
src/pii_process/api/chunk.py
src/pii_process/api/chunk_multilang.py
src/pii_process/api/document.py
src/pii_process/app/__init__.py
src/pii_process/app/doc.py
src/pii_process/app/jsonl.py
src/pii_process/writer/__init__.py
src/pii_process/writer/csv.py
src/pii_process/writer/docwriter.py