Metadata-Version: 2.1
Name: pii-process
Version: 0.1.1
Summary: Full end-to-end processing for PII (preprocess, extract, decide, transform)
Home-page: https://github.com/piisa/pii-process
Download-URL: https://github.com/piisa/pii-process/tarball/v0.1.1
Author: Paulo Villegas
Author-email: paulo.vllgs@gmail.com
License: Apache
Keywords: PIISA, PII
Classifier: Programming Language :: Python :: 3 :: Only
Classifier: License :: OSI Approved :: Apache Software License
Classifier: Development Status :: 4 - Beta
Classifier: Topic :: Software Development :: Libraries :: Application Frameworks
Requires-Python: >=3.8
Provides-Extra: test
Provides-Extra: transformers
Provides-Extra: presidio
License-File: LICENSE
